<?xml version="1.0" encoding="utf-8" ?><dwsync><file name="background.gif" server="ftp.mossor.org" local="3250656000" remote="2604467965386625792" /><file name="galerieslideshow.js" server="ftp.mossor.org" local="3307330800" remote="2604479407236177136" /><file name="page_1.html" server="ftp.mossor.org" local="3307330800" remote="2604598395010145520" /><file name="page_10.html" server="ftp.mossor.org" local="3307330800" remote="2604604115906583792" /><file name="page_11.html" server="ftp.mossor.org" local="3307330800" remote="2604609836803022064" /><file name="page_12.html" server="ftp.mossor.org" local="3307330800" remote="2604615557699460336" /><file name="page_13.html" server="ftp.mossor.org" local="3307330800" remote="2604621278595898608" /><file name="page_14.html" server="ftp.mossor.org" local="3307330800" remote="2604626999492336880" /><file name="page_15.html" server="ftp.mossor.org" local="3307330800" remote="2604695392551558384" /><file name="page_16.html" server="ftp.mossor.org" local="3307330800" remote="2604701113447996656" /><file name="page_17.html" server="ftp.mossor.org" local="3307330800" remote="2604706834344434928" /><file name="page_18.html" server="ftp.mossor.org" local="3307330800" remote="2604712555240873200" /><file name="page_19.html" server="ftp.mossor.org" local="3307330800" remote="2604718276137311472" /><file name="page_2.html" server="ftp.mossor.org" local="3307330800" remote="2604723997033749744" /><file name="page_20.html" server="ftp.mossor.org" local="3307330800" remote="2604729717930188016" /><file name="page_21.html" server="ftp.mossor.org" local="3307330800" remote="2592389022758329584" /><file name="page_22.html" server="ftp.mossor.org" local="3307330800" remote="2592394743654767856" /><file name="page_23.html" server="ftp.mossor.org" local="3307330800" remote="2592400464551206128" /><file name="page_24.html" server="ftp.mossor.org" local="3307330800" remote="2592406185447644400" /><file name="page_25.html" server="ftp.mossor.org" local="3307330800" remote="2592411906344082672" /><file name="page_26.html" server="ftp.mossor.org" local="3307330800" remote="2592417627240520944" /><file name="page_27.html" server="ftp.mossor.org" local="3307330800" remote="2592423348136959216" /><file name="page_28.html" server="ftp.mossor.org" local="3307330800" remote="2592429069033397488" /><file name="page_29.html" server="ftp.mossor.org" local="3307330800" remote="2592497462092618992" /><file name="page_3.html" server="ftp.mossor.org" local="3307330800" remote="2592503182989057264" /><file name="page_30.html" server="ftp.mossor.org" local="3307330800" remote="2592508903885495536" /><file name="page_31.html" server="ftp.mossor.org" local="3307330800" remote="2592514624781933808" /><file name="page_32.html" server="ftp.mossor.org" local="3307330800" remote="2592520345678372080" /><file name="page_33.html" server="ftp.mossor.org" local="3307330800" remote="2592526066574810352" /><file name="page_34.html" server="ftp.mossor.org" local="3307330800" remote="2592531787471248624" /><file name="page_35.html" server="ftp.mossor.org" local="3307330800" remote="2592582588344425712" /><file name="page_36.html" server="ftp.mossor.org" local="3307330800" remote="2592588309240863984" /><file name="page_37.html" server="ftp.mossor.org" local="3307330800" remote="2592594030137302256" /><file name="page_38.html" server="ftp.mossor.org" local="3307330800" remote="2592599751033740528" /><file name="page_39.html" server="ftp.mossor.org" local="3307330800" remote="2592605471930178800" /><file name="page_4.html" server="ftp.mossor.org" local="3307330800" remote="2592611192826617072" /><file name="page_40.html" server="ftp.mossor.org" local="3307330800" remote="2592616913723055344" /><file name="page_41.html" server="ftp.mossor.org" local="3307330800" remote="2592685306782276848" /><file name="page_42.html" server="ftp.mossor.org" local="3307330800" remote="2592691027678715120" /><file name="page_43.html" server="ftp.mossor.org" local="3307330800" remote="2592696748575153392" /><file name="page_44.html" server="ftp.mossor.org" local="3307330800" remote="2592702469471591664" /><file name="page_45.html" server="ftp.mossor.org" local="3307330800" remote="2592708190368029936" /><file name="page_46.html" server="ftp.mossor.org" local="3307330800" remote="2592713911264468208" /><file name="page_47.html" server="ftp.mossor.org" local="3307330800" remote="2592719632160906480" /><file name="page_48.html" server="ftp.mossor.org" local="3307330800" remote="2592130517266717936" /><file name="page_49.html" server="ftp.mossor.org" local="3307330800" remote="2592136238163156208" /><file name="page_5.html" server="ftp.mossor.org" local="3307330800" remote="2592141959059594480" /><file name="page_50.html" server="ftp.mossor.org" local="3307330800" remote="2592147679956032752" /><file name="page_51.html" server="ftp.mossor.org" local="3307330800" remote="2592153400852471024" /><file name="page_52.html" server="ftp.mossor.org" local="3307330800" remote="2592159121748909296" /><file name="page_53.html" server="ftp.mossor.org" local="3307330800" remote="2592164842645347568" /><file name="page_54.html" server="ftp.mossor.org" local="3307330800" remote="2592233235704569072" /><file name="page_55.html" server="ftp.mossor.org" local="3307330800" remote="2592238956601007344" /><file name="page_56.html" server="ftp.mossor.org" local="3307330800" remote="2592244677497445616" /><file name="page_57.html" server="ftp.mossor.org" local="3307330800" remote="2592250398393883888" /><file name="page_58.html" server="ftp.mossor.org" local="3307330800" remote="2592256119290322160" /><file name="page_59.html" server="ftp.mossor.org" local="3307330800" remote="2592261840186760432" /><file name="page_6.html" server="ftp.mossor.org" local="3307330800" remote="2592267561083198704" /><file name="page_60.html" server="ftp.mossor.org" local="3307330800" remote="2594337065304972528" /><file name="page_61.html" server="ftp.mossor.org" local="3307330800" remote="2594342786201410800" /><file name="page_62.html" server="ftp.mossor.org" local="3307330800" remote="2594348507097849072" /><file name="page_63.html" server="ftp.mossor.org" local="3307330800" remote="2594354227994287344" /><file name="page_64.html" server="ftp.mossor.org" local="3307330800" remote="2594359948890725616" /><file name="page_65.html" server="ftp.mossor.org" local="3307330800" remote="2594365669787163888" /><file name="page_66.html" server="ftp.mossor.org" local="3307330800" remote="2594371390683602160" /><file name="page_67.html" server="ftp.mossor.org" local="3307330800" remote="2594514550533512432" /><file name="page_68.html" server="ftp.mossor.org" local="3307330800" remote="2594520271429950704" /><file name="page_69.html" server="ftp.mossor.org" local="3307330800" remote="2594525992326388976" /><file name="page_7.html" server="ftp.mossor.org" local="3307330800" remote="2594531713222827248" /><file name="page_70.html" server="ftp.mossor.org" local="3307330800" remote="2594537434119265520" /><file name="page_71.html" server="ftp.mossor.org" local="3307330800" remote="2594543155015703792" /><file name="page_72.html" server="ftp.mossor.org" local="3307330800" remote="2594548875912142064" /><file name="page_73.html" server="ftp.mossor.org" local="3307330800" remote="2594590880692296944" /><file name="page_74.html" server="ftp.mossor.org" local="3307330800" remote="2594596601588735216" /><file name="page_75.html" server="ftp.mossor.org" local="3307330800" remote="2594602322485173488" /><file name="page_76.html" server="ftp.mossor.org" local="3307330800" remote="2594608043381611760" /><file name="page_77.html" server="ftp.mossor.org" local="3307330800" remote="2594613764278050032" /><file name="page_78.html" server="ftp.mossor.org" local="3307330800" remote="2594619485174488304" /><file name="page_79.html" server="ftp.mossor.org" local="3307330800" remote="2594625206070926576" /><file name="page_8.html" server="ftp.mossor.org" local="3307330800" remote="2594693599130148080" /><file name="page_80.html" server="ftp.mossor.org" local="3307330800" remote="2594699320026586352" /><file name="page_81.html" server="ftp.mossor.org" local="3307330800" remote="2594705040923024624" /><file name="page_82.html" server="ftp.mossor.org" local="3307330800" remote="2594710761819462896" /><file name="page_83.html" server="ftp.mossor.org" local="3307330800" remote="2594716482715901168" /><file name="page_84.html" server="ftp.mossor.org" local="3307330800" remote="2594722203612339440" /><file name="page_85.html" server="ftp.mossor.org" local="3307330800" remote="2594727924508777712" /><file name="page_86.html" server="ftp.mossor.org" local="3307330800" remote="2594733645405215984" /><file name="page_87.html" server="ftp.mossor.org" local="3307330800" remote="2594802038464437488" /><file name="page_88.html" server="ftp.mossor.org" local="3307330800" remote="2594807759360875760" /><file name="page_89.html" server="ftp.mossor.org" local="3307330800" remote="2594813480257314032" /><file name="page_9.html" server="ftp.mossor.org" local="3307330800" remote="2594819201153752304" /><file name="page_90.html" server="ftp.mossor.org" local="3307330800" remote="2594824922050190576" /></dwsync>